{
  "name": "Castle Mistmoore",
  "expansion": "exp03",
  "category": "Faydwer",
  "levels": "70",
  "connections": [
    {
      "key": "exp03_dun_mistmoore_catacombs"
    },
    {
      "key": "exp03_rgn_loping_plains"
    }
  ],
  "npcs": [
    {
      "name": "Arimei V'Dhiver",
      "drops": [
        {
          "gamelink": "\\aITEM 397113180 -284265364:small bag of compost\\/a",
          "chest": false
        }
      ],
      "faction_changes": [
        {
          "name": "Mistmoore",
          "value": -100
        },
        {
          "name": "The Lyrech",
          "value": 50
        }
      ]
    },
    {
      "name": "Arivar Z'Devzha",
      "drops": [
        {
          "gamelink": "\\aITEM -977204729 -1733118177:Emerald Amulet\\/a",
          "chest": false
        }
      ],
      "faction_changes": [
        {
          "name": "Mistmoore",
          "value": -100
        },
        {
          "name": "The Lyrech",
          "value": 50
        }
      ]
    },
    {
      "name": "Divar B'Ingker",
      "drop_coin_min": 4329,
      "drop_coin_max": 4329,
      "faction_changes": [
        {
          "name": "Mistmoore",
          "value": -100
        },
        {
          "name": "The Lyrech",
          "value": 50
        }
      ]
    },
    {
      "name": "Drela K'Tazinez",
      "drops": [
        {
          "gamelink": "\\aITEM 1133033886 1112751626:Emerald Scrying Stone\\/a",
          "chest": false
        }
      ],
      "faction_changes": [
        {
          "name": "Mistmoore",
          "value": -100
        },
        {
          "name": "The Lyrech",
          "value": 50
        }
      ]
    },
    {
      "name": "Dzhower S'Vinimi",
      "drops": [
        {
          "gamelink": "\\aITEM 1871773141 25375289:Faywax Sealed Document\\/a",
          "chest": false
        }
      ],
      "faction_changes": [
        {
          "name": "Mistmoore",
          "value": -100
        },
        {
          "name": "The Lyrech",
          "value": 50
        }
      ]
    },
    {
      "name": "a gypsy musician",
      "drops": [
        {
          "gamelink": "\\aITEM -1186025986 -1217159832:Beryllium Relic\\/a",
          "chest": false
        },
        {
          "gamelink": "\\aITEM 1133033886 1112751626:Emerald Scrying Stone\\/a",
          "chest": false
        }
      ],
      "faction_changes": [
        {
          "name": "Mistmoore",
          "value": -100
        },
        {
          "name": "The Lyrech",
          "value": 50
        }
      ]
    },
    {
      "name": "Irinez K'Tyrimi",
      "drops": [
        {
          "gamelink": "\\aITEM 2064770571 1318583467:statue of Veeshan\\/a",
          "chest": false
        }
      ],
      "faction_changes": [
        {
          "name": "Mistmoore",
          "value": -100
        },
        {
          "name": "The Lyrech",
          "value": 50
        }
      ]
    },
    {
      "name": "Ixhrez Z'Vezilhi",
      "drop_coin_min": 38782,
      "drop_coin_max": 38782,
      "faction_changes": [
        {
          "name": "Mistmoore",
          "value": -100
        },
        {
          "name": "The Lyrech",
          "value": 50
        }
      ]
    },
    {
      "name": "a jeering gargoyle",
      "drop_coin_min": 4729,
      "drop_coin_max": 4729,
      "faction_changes": [
        {
          "name": "Mistmoore",
          "value": -100
        },
        {
          "name": "The Lyrech",
          "value": 50
        }
      ]
    },
    {
      "name": "Jravar V'Vezimei",
      "drops": [
        {
          "gamelink": "\\aITEM 728229990 1181299130:a vampiric incisor\\/a",
          "chest": false
        }
      ],
      "drop_coin_min": 4038,
      "drop_coin_max": 4038,
      "faction_changes": [
        {
          "name": "Mistmoore",
          "value": -100
        },
        {
          "name": "The Lyrech",
          "value": 50
        }
      ]
    },
    {
      "name": "Jylevzha Z'Dwivar",
      "drops": [
        {
          "gamelink": "\\aITEM 1133033886 1112751626:Emerald Scrying Stone\\/a",
          "chest": false
        },
        {
          "gamelink": "\\aITEM 728229990 1181299130:a vampiric incisor\\/a",
          "chest": false
        }
      ],
      "faction_changes": [
        {
          "name": "Mistmoore",
          "value": -100
        },
        {
          "name": "The Lyrech",
          "value": 50
        }
      ]
    },
    {
      "name": "Jzipoz T'Vininek",
      "drops": [
        {
          "gamelink": "\\aITEM 204190846 1133292751:war fist\\/a",
          "chest": false
        }
      ],
      "faction_changes": [
        {
          "name": "Mistmoore",
          "value": -100
        },
        {
          "name": "The Lyrech",
          "value": 50
        }
      ]
    },
    {
      "name": "Kreque Z'Qhomer",
      "drop_coin_min": 4931,
      "drop_coin_max": 4931,
      "faction_changes": [
        {
          "name": "Mistmoore",
          "value": -100
        },
        {
          "name": "The Lyrech",
          "value": 50
        }
      ]
    },
    {
      "name": "Krivizh D'Xyla",
      "drops": [
        {
          "gamelink": "\\aITEM -977204729 -1733118177:Emerald Amulet\\/a",
          "chest": false
        }
      ],
      "faction_changes": [
        {
          "name": "Mistmoore",
          "value": -100
        },
        {
          "name": "The Lyrech",
          "value": 50
        }
      ]
    },
    {
      "name": "Kzeque Z'Jylevar",
      "drop_coin_min": 3615,
      "drop_coin_max": 3615,
      "faction_changes": [
        {
          "name": "Mistmoore",
          "value": -100
        },
        {
          "name": "The Lyrech",
          "value": 50
        }
      ]
    },
    {
      "name": "Kzever T'Vythiver",
      "drops": [
        {
          "gamelink": "\\aITEM 1133033886 1112751626:Emerald Scrying Stone\\/a",
          "chest": false
        }
      ],
      "faction_changes": [
        {
          "name": "Mistmoore",
          "value": -100
        },
        {
          "name": "The Lyrech",
          "value": 50
        }
      ]
    },
    {
      "name": "a leering gargoyle",
      "drop_coin_min": 5158,
      "drop_coin_max": 8728,
      "faction_changes": [
        {
          "name": "Mistmoore",
          "value": -100
        },
        {
          "name": "The Lyrech",
          "value": 50
        }
      ]
    },
    {
      "name": "Nhivzha K'Nzhexi",
      "drop_coin_min": 6232,
      "drop_coin_max": 6232,
      "faction_changes": [
        {
          "name": "Mistmoore",
          "value": -100
        },
        {
          "name": "The Lyrech",
          "value": 50
        }
      ]
    },
    {
      "name": "Oxanez K'Kvhiwer",
      "drops": [
        {
          "gamelink": "\\aITEM 728229990 1181299130:a vampiric incisor\\/a",
          "chest": false
        }
      ],
      "faction_changes": [
        {
          "name": "Mistmoore",
          "value": -100
        },
        {
          "name": "The Lyrech",
          "value": 50
        }
      ]
    },
    {
      "name": "Ozimi H'Izhame",
      "drop_coin_min": 8772,
      "drop_coin_max": 8772,
      "faction_changes": [
        {
          "name": "Mistmoore",
          "value": -100
        },
        {
          "name": "The Lyrech",
          "value": 50
        }
      ]
    },
    {
      "name": "Qhepoz V'Dwiwer",
      "drops": [
        {
          "gamelink": "\\aITEM 728229990 1181299130:a vampiric incisor\\/a",
          "chest": false
        }
      ],
      "faction_changes": [
        {
          "name": "Mistmoore",
          "value": -100
        },
        {
          "name": "The Lyrech",
          "value": 50
        }
      ]
    },
    {
      "name": "Qhovzha J'Setime",
      "drops": [
        {
          "gamelink": "\\aITEM 728229990 1181299130:a vampiric incisor\\/a",
          "chest": false
        }
      ],
      "drop_coin_min": 7515,
      "drop_coin_max": 7515,
      "faction_changes": [
        {
          "name": "Mistmoore",
          "value": -100
        },
        {
          "name": "The Lyrech",
          "value": 50
        }
      ]
    },
    {
      "name": "Rethiver Z'Rzhezsi",
      "drops": [
        {
          "gamelink": "\\aITEM 1133033886 1112751626:Emerald Scrying Stone\\/a",
          "chest": false
        }
      ],
      "faction_changes": [
        {
          "name": "Mistmoore",
          "value": -100
        },
        {
          "name": "The Lyrech",
          "value": 50
        }
      ]
    },
    {
      "name": "Rhila D'Athelhi",
      "drops": [
        {
          "gamelink": "\\aITEM -348783277 -2030041114:large meaty bone\\/a",
          "chest": false
        }
      ],
      "faction_changes": [
        {
          "name": "Mistmoore",
          "value": -100
        },
        {
          "name": "The Lyrech",
          "value": 50
        }
      ]
    },
    {
      "name": "a silverfang warrior",
      "drops": [
        {
          "gamelink": "\\aITEM 1871773141 25375289:Faywax Sealed Document\\/a",
          "chest": false
        }
      ],
      "drop_coin_min": 7300,
      "drop_coin_max": 7660,
      "faction_changes": [
        {
          "name": "Mistmoore",
          "value": -100
        },
        {
          "name": "The Lyrech",
          "value": 50
        }
      ]
    },
    {
      "name": "Szela Z'Qhovar",
      "drop_coin_min": 5133,
      "drop_coin_max": 5133,
      "faction_changes": [
        {
          "name": "Mistmoore",
          "value": -100
        },
        {
          "name": "The Lyrech",
          "value": 50
        }
      ]
    },
    {
      "name": "Szeme T'Athever",
      "drop_coin_min": 7491,
      "drop_coin_max": 7491,
      "faction_changes": [
        {
          "name": "Mistmoore",
          "value": -100
        },
        {
          "name": "The Lyrech",
          "value": 50
        }
      ]
    },
    {
      "name": "Tazime Z'Szeque",
      "drop_coin_min": 7893,
      "drop_coin_max": 7893,
      "faction_changes": [
        {
          "name": "Mistmoore",
          "value": -100
        },
        {
          "name": "The Lyrech",
          "value": 50
        }
      ]
    },
    {
      "name": "Tyhamer Z'Vythinek",
      "drop_coin_min": 6108,
      "drop_coin_max": 6108,
      "faction_changes": [
        {
          "name": "Mistmoore",
          "value": -100
        },
        {
          "name": "The Lyrech",
          "value": 50
        }
      ]
    },
    {
      "name": "Vala S'Vuevar",
      "drops": [
        {
          "gamelink": "\\aITEM -1186025986 -1217159832:Beryllium Relic\\/a",
          "chest": false
        },
        {
          "gamelink": "\\aITEM -977204729 -1733118177:Emerald Amulet\\/a",
          "chest": false
        }
      ],
      "faction_changes": [
        {
          "name": "Mistmoore",
          "value": -100
        },
        {
          "name": "The Lyrech",
          "value": 50
        }
      ]
    },
    {
      "name": "Vethinez V'Zaxi",
      "drops": [
        {
          "gamelink": "\\aITEM 1871773141 25375289:Faywax Sealed Document\\/a",
          "chest": false
        }
      ],
      "faction_changes": [
        {
          "name": "Mistmoore",
          "value": -100
        },
        {
          "name": "The Lyrech",
          "value": 50
        }
      ]
    },
    {
      "name": "a vigilant Mistmoore guardian",
      "drops": [
        {
          "gamelink": "\\aITEM -1186025986 -1217159832:Beryllium Relic\\/a",
          "chest": false
        },
        {
          "gamelink": "\\aITEM 1133033886 1112751626:Emerald Scrying Stone\\/a",
          "chest": false
        },
        {
          "gamelink": "\\aITEM 941781269 543692388:ethereal strand\\/a",
          "chest": false
        }
      ],
      "faction_changes": [
        {
          "name": "Mistmoore",
          "value": -100
        },
        {
          "name": "The Lyrech",
          "value": 50
        }
      ]
    },
    {
      "name": "Vinipoz Z'Rethiver",
      "drop_coin_min": 36924,
      "drop_coin_max": 36924,
      "faction_changes": [
        {
          "name": "Mistmoore",
          "value": -100
        },
        {
          "name": "The Lyrech",
          "value": 50
        }
      ]
    },
    {
      "name": "Vinixi B'Rxolhi",
      "drops": [
        {
          "gamelink": "\\aITEM 397113180 -284265364:small bag of compost\\/a",
          "chest": false
        }
      ],
      "faction_changes": [
        {
          "name": "Mistmoore",
          "value": -100
        },
        {
          "name": "The Lyrech",
          "value": 50
        }
      ]
    },
    {
      "name": "Vzhime D'Drexi",
      "drops": [
        {
          "gamelink": "\\aITEM 728229990 1181299130:a vampiric incisor\\/a",
          "chest": false
        }
      ],
      "faction_changes": [
        {
          "name": "Mistmoore",
          "value": -100
        },
        {
          "name": "The Lyrech",
          "value": 50
        }
      ]
    },
    {
      "name": "a watchful Mistmoore protector",
      "drops": [
        {
          "gamelink": "\\aITEM -1186025986 -1217159832:Beryllium Relic\\/a",
          "chest": false
        },
        {
          "gamelink": "\\aITEM 1133033886 1112751626:Emerald Scrying Stone\\/a",
          "chest": false
        },
        {
          "gamelink": "\\aITEM 941781269 543692388:ethereal strand\\/a",
          "chest": false
        }
      ],
      "faction_changes": [
        {
          "name": "Mistmoore",
          "value": -100
        },
        {
          "name": "The Lyrech",
          "value": 50
        }
      ]
    },
    {
      "name": "Xawer Y'Zsiwer",
      "drop_coin_min": 6032,
      "drop_coin_max": 6032,
      "faction_changes": [
        {
          "name": "Mistmoore",
          "value": -100
        },
        {
          "name": "The Lyrech",
          "value": 50
        }
      ]
    },
    {
      "name": "Xivar V'Vuewer",
      "drops": [
        {
          "gamelink": "\\aITEM 1871773141 25375289:Faywax Sealed Document\\/a",
          "chest": false
        }
      ],
      "drop_coin_min": 65065,
      "drop_coin_max": 65065,
      "faction_changes": [
        {
          "name": "Mistmoore",
          "value": -100
        },
        {
          "name": "The Lyrech",
          "value": 50
        }
      ]
    },
    {
      "name": "Zala K'Zsiker",
      "drops": [
        {
          "gamelink": "\\aITEM -977204729 -1733118177:Emerald Amulet\\/a",
          "chest": false
        }
      ],
      "faction_changes": [
        {
          "name": "Mistmoore",
          "value": -100
        },
        {
          "name": "The Lyrech",
          "value": 50
        }
      ]
    },
    {
      "name": "Zawer D'Aripoz",
      "drops": [
        {
          "gamelink": "\\aITEM 728229990 1181299130:a vampiric incisor\\/a",
          "chest": false
        }
      ],
      "faction_changes": [
        {
          "name": "Mistmoore",
          "value": -100
        },
        {
          "name": "The Lyrech",
          "value": 50
        }
      ]
    },
    {
      "name": "Zimer Y'Dfazsi",
      "drops": [
        {
          "gamelink": "\\aITEM -1186025986 -1217159832:Beryllium Relic\\/a",
          "chest": false
        }
      ],
      "faction_changes": [
        {
          "name": "Mistmoore",
          "value": -100
        },
        {
          "name": "The Lyrech",
          "value": 50
        }
      ]
    }
  ],
  "shinies": [
    {
      "gamelink": "\\aITEM 411498120 1576471628:orange stained glass fragment\\/a"
    },
    {
      "gamelink": "\\aITEM 1889880824 -672175826:red stained glass fragment\\/a"
    },
    {
      "gamelink": "\\aITEM -810017367 -895431508:slayer tools - mirror\\/a"
    },
    {
      "gamelink": "\\aITEM -1454467192 -1012450338:slayer tools - purified water\\/a"
    },
    {
      "gamelink": "\\aITEM 246767173 -1506535107:white stained glass fragment\\/a"
    }
  ]
}