{
  "name": "Longshadow Alley: Daeneth Cloister",
  "category": "Villages",
  "subcategory": "Freeport",
  "maps": [
    {
      "zonerect": "-185.63,-147.51,165.21,126.03"
    }
  ],
  "connections": [
    {
      "key": "freeport_combined"
    }
  ],
  "npcs": [
    {
      "name": "a Freeblood savage",
      "utterances": [
        "Nooo...can't stop the thirst...Arrrggg!",
        "Arrrgg...the pain...must feed..."
      ]
    },
    {
      "name": "Kora N'Vaxin"
    },
    {
      "name": "a loyal worshiper",
      "utterances": [
        "What do you want?",
        "Unh...it's not possible."
      ]
    },
    {
      "name": "a Nerian guard",
      "utterances": [
        "Say nothing of what you see, or else!",
        "All Thexian hearts belong to the queen; beating or not."
      ]
    },
    {
      "name": "a Thexian rebel",
      "utterances": [
        "Look what strolled into the spider's web!",
        "Hold them and I'll return with help!",
        "There is no escape for you now!",
        "I will have vengeance!"
      ],
      "drops": [
        {
          "gamelink": "\\aITEM 1248460866 -2081525494:Advanced Adornments Volume 1\\/a",
          "chest": false
        }
      ],
      "drop_coin_min": 8,
      "drop_coin_max": 8
    }
  ]
}