{
  "name": "Bar of Brell",
  "name_sortable": "barofbrell",
  "category": "Other",
  "maps": [
    {
      "name": "Basement"
    },
    {
      "name": "Main Floor"
    }
  ],
  "connections": [
    {
      "key": "tutorial_island02_epic02_serellian_bar"
    },
    {
      "key": "antonica"
    },
    {
      "key": "halas"
    },
    {
      "key": "exp03_rgn_greater_faydark"
    },
    {
      "key": "exile_city"
    },
    {
      "key": "commonlands"
    },
    {
      "key": "exp04_rgn_timorous_deep"
    }
  ],
  "npcs": [
    {
      "name": "Balin Copperfoot",
      "name_sortable": "balincopperfoot",
      "purpose": "Merchant",
      "locations": [
        "331.79,-20.99,138.31"
      ],
      "store": [
        {
          "gamelink": "\\aITEM -199767560 1856995189:Brewday Accoutrements to Craft XV\\/a",
          "prices": [
            {
              "coin": 6090
            }
          ]
        },
        {
          "gamelink": "\\aITEM 935753550 -1081133924 0 0 0:Brewday Party Fireworks Launcher\\/a",
          "prices": [
            {
              "currency": {
                "gamelink": "\\aITEM -364189726 2052492544 0 0 0:Beer Token\\/a",
                "amount": 5
              }
            }
          ]
        },
        {
          "gamelink": "\\aITEM 1693328161 -803170838 0 0 0:Claws of the Stone Sculpture\\/a",
          "prices": [
            {
              "currency": {
                "gamelink": "\\aITEM -364189726 2052492544 0 0 0:Beer Token\\/a",
                "amount": 15
              }
            }
          ]
        },
        {
          "gamelink": "\\aITEM -1583800243 855827166 0 0 0:Drinking Dhalgar Skeleton Plushie\\/a",
          "prices": [
            {
              "currency": {
                "gamelink": "\\aITEM -364189726 2052492544 0 0 0:Beer Token\\/a",
                "amount": 4
              }
            }
          ]
        },
        {
          "gamelink": "\\aITEM -1560014143 713396151 0 0 0:Emerald Zelniak\\/a",
          "prices": [
            {
              "currency": {
                "gamelink": "\\aITEM -364189726 2052492544 0 0 0:Beer Token\\/a",
                "amount": 10
              }
            }
          ]
        },
        {
          "gamelink": "\\aITEM -196047632 601150509 0 0 0:Petamorph Wand: Krausen Wisp\\/a",
          "prices": [
            {
              "currency": {
                "gamelink": "\\aITEM -364189726 2052492544 0 0 0:Beer Token\\/a",
                "amount": 15
              }
            }
          ]
        },
        {
          "gamelink": "\\aITEM 1547376083 2116596810 0 0 0:Wall-embedded Keg\\/a",
          "prices": [
            {
              "currency": {
                "gamelink": "\\aITEM -364189726 2052492544 0 0 0:Beer Token\\/a",
                "amount": 5
              }
            }
          ]
        }
      ]
    },
    {
      "name": "Blingo",
      "name_sortable": "blingo",
      "purpose": "The Burglars",
      "locations": [
        "359.38,-21.0,137.53"
      ]
    },
    {
      "name": "Bouncer McGattle",
      "name_sortable": "bouncermcgattle",
      "locations": [
        "327.0,-20.99,144.12"
      ]
    },
    {
      "name": "Buzzed",
      "name_sortable": "buzzed",
      "purpose": "Snoogle's Portable Flying Kegerator",
      "locations": [
        "335.5,-20.01,136.17"
      ],
      "utterances": [
        "Dispense Ale?",
        "*BZZZT* Error. Mechanical malfunction. Run self-diagnostic?",
        "Self-diagnostic complete. Multiple part failure. Replacement of parts required.",
        "Feysteel * BZZZT ZZZAP* acquired in Gnomeland Security. Incarnadine * ZZZAP BZZZT * acquired in Dropship Landing Zone.",
        "Maintenance required. Must obtain replacement parts.",
        "Affirmative. Now performing self-maintenance. Please wait.",
        "Maintenance concluded. Dispense Ale?",
        "Error. Ale level too low.",
        "Awaiting Seamist malt and Haoaera pepper.",
        "Ingredients confirmed and added. Brewing successful!"
      ]
    },
    {
      "name": "Colonel Mutt Fiddletwang",
      "name_sortable": "colonelmuttfiddletwang",
      "locations": [
        "349.69,-21.0,141.13"
      ]
    },
    {
      "name": "Digret Runebrand",
      "name_sortable": "digretrunebrand",
      "purpose": "Merchant",
      "locations": [
        "354.25,-20.99,137.1"
      ],
      "store": [
        {
          "gamelink": "\\aITEM -534159545 -1796679845 0 0 0:a Strange Cabbage\\/a",
          "prices": [
            {
              "currency": {
                "gamelink": "\\aITEM -364189726 2052492544 0 0 0:Beer Token\\/a",
                "amount": 10
              }
            }
          ]
        },
        {
          "gamelink": "\\aITEM 432764206 -2006100958 0 0 0:Ancient Kaladim Door\\/a",
          "prices": [
            {
              "currency": {
                "gamelink": "\\aITEM -364189726 2052492544 0 0 0:Beer Token\\/a",
                "amount": 15
              }
            }
          ]
        },
        {
          "gamelink": "\\aITEM 1490266664 35372691 0 0 0:Animated Hops Plushie\\/a",
          "prices": [
            {
              "currency": {
                "gamelink": "\\aITEM -364189726 2052492544 0 0 0:Beer Token\\/a",
                "amount": 4
              }
            }
          ]
        },
        {
          "gamelink": "\\aITEM 1321127702 -1225566911 0 0 0:Arctic Badger\\/a",
          "prices": [
            {
              "currency": {
                "gamelink": "\\aITEM -364189726 2052492544 0 0 0:Beer Token\\/a",
                "amount": 10
              }
            }
          ]
        },
        {
          "gamelink": "\\aITEM -1321931579 -94712304 0 0 0:Armored Gnoll Plushie\\/a",
          "prices": [
            {
              "currency": {
                "gamelink": "\\aITEM -364189726 2052492544 0 0 0:Beer Token\\/a",
                "amount": 4
              }
            }
          ]
        },
        {
          "gamelink": "\\aITEM 1778572418 604076419 0 0 0:Ashenfell Terramancer Plushie\\/a",
          "prices": [
            {
              "currency": {
                "gamelink": "\\aITEM -364189726 2052492544 0 0 0:Beer Token\\/a",
                "amount": 4
              }
            }
          ]
        },
        {
          "gamelink": "\\aITEM 734346179 1707515586 0 0 0:Ashenfell Weaponsmith Plushie\\/a",
          "prices": [
            {
              "currency": {
                "gamelink": "\\aITEM -364189726 2052492544 0 0 0:Beer Token\\/a",
                "amount": 4
              }
            }
          ]
        },
        {
          "gamelink": "\\aITEM -1920492191 1664985932 0 0 0:Barrel Room Door\\/a",
          "prices": [
            {
              "currency": {
                "gamelink": "\\aITEM -364189726 2052492544 0 0 0:Beer Token\\/a",
                "amount": 30
              }
            }
          ]
        },
        {
          "gamelink": "\\aITEM -1647824079 1990618783 0 0 0:Barrel Room Sign\\/a",
          "prices": [
            {
              "currency": {
                "gamelink": "\\aITEM -364189726 2052492544 0 0 0:Beer Token\\/a",
                "amount": 15
              }
            }
          ]
        },
        {
          "gamelink": "\\aITEM 1079727220 -1300797355 0 0 0:Boar's Head Wall Trophy\\/a",
          "prices": [
            {
              "currency": {
                "gamelink": "\\aITEM -364189726 2052492544 0 0 0:Beer Token\\/a",
                "amount": 5
              }
            }
          ]
        },
        {
          "gamelink": "\\aITEM 1495869422 784633480 0 0 0:Boarfiend Plushie\\/a",
          "prices": [
            {
              "currency": {
                "gamelink": "\\aITEM -364189726 2052492544 0 0 0:Beer Token\\/a",
                "amount": 4
              }
            }
          ]
        },
        {
          "gamelink": "\\aITEM 1403505503 736505242 0 0 0:Boozy Glow Skimmer\\/a",
          "prices": [
            {
              "currency": {
                "gamelink": "\\aITEM -364189726 2052492544 0 0 0:Beer Token\\/a",
                "amount": 5
              }
            }
          ]
        },
        {
          "gamelink": "\\aITEM 311383860 -823673416 0 0 0:Bouncy Grungetalon Chest\\/a",
          "prices": [
            {
              "currency": {
                "gamelink": "\\aITEM -364189726 2052492544 0 0 0:Beer Token\\/a",
                "amount": 10
              }
            }
          ]
        },
        {
          "gamelink": "\\aITEM 179432745 279556945 0 0 0:Brewcrew Buccaneer Boots\\/a"
        },
        {
          "gamelink": "\\aITEM 1521390339 122953919 0 0 0:Brewcrew Buccaneer Cap\\/a",
          "prices": [
            {
              "currency": {
                "gamelink": "\\aITEM -364189726 2052492544 0 0 0:Beer Token\\/a",
                "amount": 6
              }
            }
          ]
        },
        {
          "gamelink": "\\aITEM 106243381 474839885 0 0 0:Brewcrew Buccaneer Shirt\\/a",
          "prices": [
            {
              "currency": {
                "gamelink": "\\aITEM -364189726 2052492544 0 0 0:Beer Token\\/a",
                "amount": 8
              }
            }
          ]
        },
        {
          "gamelink": "\\aITEM -1466385505 -1012060534 0 0 0:Brewcrew Buccaneer Sleeves\\/a",
          "prices": [
            {
              "currency": {
                "gamelink": "\\aITEM -364189726 2052492544 0 0 0:Beer Token\\/a",
                "amount": 6
              }
            }
          ]
        },
        {
          "gamelink": "\\aITEM 2072948213 372800651 0 0 0:Brewcrew Buccaneer Trousers\\/a",
          "prices": [
            {
              "currency": {
                "gamelink": "\\aITEM -364189726 2052492544 0 0 0:Beer Token\\/a",
                "amount": 8
              }
            }
          ]
        },
        {
          "gamelink": "\\aITEM 348014321 1538319150 0 0 0:Brewcrew Captain's Hat\\/a",
          "prices": [
            {
              "currency": {
                "gamelink": "\\aITEM -364189726 2052492544 0 0 0:Beer Token\\/a",
                "amount": 8
              }
            }
          ]
        },
        {
          "gamelink": "\\aITEM -1634329078 829093269 0 0 0:Brewday Accoutrements to Craft\\/a",
          "prices": [
            {
              "coin": 6090
            }
          ]
        },
        {
          "gamelink": "\\aITEM 499896448 531744878 0 0 0:Brewday Accoutrements to Craft II\\/a",
          "prices": [
            {
              "coin": 6090
            }
          ]
        },
        {
          "gamelink": "\\aITEM 70023639 1242607258 0 0 0:Brewday Accoutrements to Craft III\\/a",
          "prices": [
            {
              "coin": 6090
            }
          ]
        },
        {
          "gamelink": "\\aITEM -1530279655 -280392903 0 0 0:Brewday Accoutrements to Craft IV\\/a",
          "prices": [
            {
              "coin": 6090
            }
          ]
        },
        {
          "gamelink": "\\aITEM -1712550979 -624004766 0 0 0:Brewday Accoutrements to Craft IX\\/a",
          "prices": [
            {
              "coin": 6090
            }
          ]
        },
        {
          "gamelink": "\\aITEM 1888737265 -622981958 0 0 0:Brewday Accoutrements to Craft V\\/a",
          "prices": [
            {
              "coin": 6090
            }
          ]
        },
        {
          "gamelink": "\\aITEM -797546689 -157086921 0 0 0:Brewday Accoutrements to Craft VI\\/a",
          "prices": [
            {
              "coin": 6090
            }
          ]
        },
        {
          "gamelink": "\\aITEM -366366676 -389681044 0 0 0:Brewday Accoutrements to Craft VII\\/a",
          "prices": [
            {
              "coin": 6090
            }
          ]
        },
        {
          "gamelink": "\\aITEM 1254883554 1273762231 0 0 0:Brewday Accoutrements to Craft VIII\\/a",
          "prices": [
            {
              "coin": 6090
            }
          ]
        },
        {
          "gamelink": "\\aITEM 956906355 -998665535 0 0 0:Brewday Accoutrements to Craft X\\/a",
          "prices": [
            {
              "coin": 6090
            }
          ]
        },
        {
          "gamelink": "\\aITEM 437387267 -475565440 0 0 0:Brewday Accoutrements to Craft XI\\/a",
          "prices": [
            {
              "coin": 6090
            }
          ]
        },
        {
          "gamelink": "\\aITEM -1158172467 -497296026 0 0 0:Brewday Accoutrements to Craft XII\\/a",
          "prices": [
            {
              "coin": 6090
            }
          ]
        },
        {
          "gamelink": "\\aITEM -2136447010 -1422694780 0 0 0:Brewday Accoutrements to Craft XIII\\/a",
          "prices": [
            {
              "coin": 6090
            }
          ]
        },
        {
          "gamelink": "\\aITEM 541972240 1867763859 0 0 0:Brewday Accoutrements to Craft XIV\\/a",
          "prices": [
            {
              "coin": 6090
            }
          ]
        },
        {
          "gamelink": "\\aITEM 740762776 1963381736 0 0 0:Brewday High-tech Distilleries\\/a",
          "prices": [
            {
              "coin": 6090
            }
          ]
        },
        {
          "gamelink": "\\aITEM 461984733 1834771780 0 0 0:Brewday Reveler's Cloak\\/a",
          "prices": [
            {
              "currency": {
                "gamelink": "\\aITEM -364189726 2052492544 0 0 0:Beer Token\\/a",
                "amount": 5
              }
            }
          ]
        },
        {
          "gamelink": "\\aITEM -1744152352 -459446250 0 0 0:Brewday Reveler's Finery\\/a",
          "prices": [
            {
              "currency": {
                "gamelink": "\\aITEM -364189726 2052492544 0 0 0:Beer Token\\/a",
                "amount": 20
              }
            }
          ]
        },
        {
          "gamelink": "\\aITEM 577181919 203942901 0 0 0:Brewday Reveler's Hat\\/a",
          "prices": [
            {
              "currency": {
                "gamelink": "\\aITEM -364189726 2052492544 0 0 0:Beer Token\\/a",
                "amount": 8
              }
            }
          ]
        },
        {
          "gamelink": "\\aITEM -1083915293 -176071747 0 0 0:Briarwood Keg Door\\/a",
          "prices": [
            {
              "currency": {
                "gamelink": "\\aITEM -364189726 2052492544 0 0 0:Beer Token\\/a",
                "amount": 30
              }
            }
          ]
        },
        {
          "gamelink": "\\aITEM -1813123319 1588135424 0 0 0:Brick Whiskey Distillery\\/a",
          "prices": [
            {
              "currency": {
                "gamelink": "\\aITEM -364189726 2052492544 0 0 0:Beer Token\\/a",
                "amount": 15
              }
            }
          ]
        },
        {
          "gamelink": "\\aITEM -1821319669 -911699595 0 0 0:Bubbling Kegs Cordon\\/a",
          "prices": [
            {
              "coin": 12000
            }
          ]
        },
        {
          "gamelink": "\\aITEM -494591137 -1252363778 0 0 0:Bubbling Kegs Streamer\\/a",
          "prices": [
            {
              "coin": 12000
            }
          ]
        },
        {
          "gamelink": "\\aITEM -641752553 1501504674 0 0 0:Calcite Stalagmaw\\/a",
          "prices": [
            {
              "currency": {
                "gamelink": "\\aITEM -364189726 2052492544 0 0 0:Beer Token\\/a",
                "amount": 10
              }
            }
          ]
        },
        {
          "gamelink": "\\aITEM 34324027 -1862782571 0 0 0:Clan McMarrin Boots\\/a",
          "prices": [
            {
              "currency": {
                "gamelink": "\\aITEM -364189726 2052492544 0 0 0:Beer Token\\/a",
                "amount": 3
              }
            }
          ]
        },
        {
          "gamelink": "\\aITEM -729964471 -1305423148 0 0 0:Clan McMarrin Gauntlets\\/a",
          "prices": [
            {
              "currency": {
                "gamelink": "\\aITEM -364189726 2052492544 0 0 0:Beer Token\\/a",
                "amount": 3
              }
            }
          ]
        },
        {
          "gamelink": "\\aITEM 1262595841 1782618829 0 0 0:Clan McMarrin Helm\\/a",
          "prices": [
            {
              "currency": {
                "gamelink": "\\aITEM -364189726 2052492544 0 0 0:Beer Token\\/a",
                "amount": 6
              }
            }
          ]
        },
        {
          "gamelink": "\\aITEM 881152331 360998023 0 0 0:Clan McMarrin Kilt\\/a",
          "prices": [
            {
              "currency": {
                "gamelink": "\\aITEM -364189726 2052492544 0 0 0:Beer Token\\/a",
                "amount": 8
              }
            }
          ]
        },
        {
          "gamelink": "\\aITEM 571392952 1871535773 0 0 0:Clan McMarrin Sleeves\\/a",
          "prices": [
            {
              "currency": {
                "gamelink": "\\aITEM -364189726 2052492544 0 0 0:Beer Token\\/a",
                "amount": 6
              }
            }
          ]
        },
        {
          "gamelink": "\\aITEM 823557549 -1545211389 0 0 0:Clan McMarrin Tunic\\/a",
          "prices": [
            {
              "currency": {
                "gamelink": "\\aITEM -364189726 2052492544 0 0 0:Beer Token\\/a",
                "amount": 8
              }
            }
          ]
        },
        {
          "gamelink": "\\aITEM -978895773 -203371751 0 0 0:Cloak of the Duke of Below\\/a",
          "prices": [
            {
              "currency": {
                "gamelink": "\\aITEM -364189726 2052492544 0 0 0:Beer Token\\/a",
                "amount": 5
              }
            }
          ]
        },
        {
          "gamelink": "\\aITEM 2126296422 1900938190 0 0 0:Clover Explosion Tile\\/a",
          "prices": [
            {
              "currency": {
                "gamelink": "\\aITEM -364189726 2052492544 0 0 0:Beer Token\\/a",
                "amount": 20
              }
            }
          ]
        },
        {
          "gamelink": "\\aITEM -451802096 1560107396 0 0 0:Coastal Basilisk\\/a",
          "prices": [
            {
              "currency": {
                "gamelink": "\\aITEM -364189726 2052492544 0 0 0:Beer Token\\/a",
                "amount": 10
              }
            }
          ]
        },
        {
          "gamelink": "\\aITEM -1335896576 1806054929 0 0 0:Cutting a Rug\\/a",
          "prices": [
            {
              "currency": {
                "gamelink": "\\aITEM -364189726 2052492544 0 0 0:Beer Token\\/a",
                "amount": 15
              }
            }
          ]
        },
        {
          "gamelink": "\\aITEM -693767992 898610244 0 0 0:Emerald Zelniak Calf Plushie\\/a",
          "prices": [
            {
              "currency": {
                "gamelink": "\\aITEM -364189726 2052492544 0 0 0:Beer Token\\/a",
                "amount": 4
              }
            }
          ]
        },
        {
          "gamelink": "\\aITEM -1769287199 1704070703 0 0 0:Emeraldscale Drakota\\/a",
          "prices": [
            {
              "currency": {
                "gamelink": "\\aITEM -364189726 2052492544 0 0 0:Beer Token\\/a",
                "amount": 200
              }
            }
          ]
        },
        {
          "gamelink": "\\aITEM -1875876327 1948844565 0 0 0:Flying Mossy Baby Dragon Plushie\\/a",
          "prices": [
            {
              "currency": {
                "gamelink": "\\aITEM -364189726 2052492544 0 0 0:Beer Token\\/a",
                "amount": 4
              }
            }
          ]
        },
        {
          "gamelink": "\\aITEM -104100808 -1277193174 0 0 0:Frothbark Kobold Plushie\\/a",
          "prices": [
            {
              "currency": {
                "gamelink": "\\aITEM -364189726 2052492544 0 0 0:Beer Token\\/a",
                "amount": 4
              }
            }
          ]
        },
        {
          "gamelink": "\\aITEM -278080292 1615877288 0 0 0:Glacierbane Axe Replica\\/a",
          "prices": [
            {
              "currency": {
                "gamelink": "\\aITEM -364189726 2052492544 0 0 0:Beer Token\\/a",
                "amount": 5
              }
            }
          ]
        },
        {
          "gamelink": "\\aITEM -1323246135 33321775 0 0 0:Gnoll Guard Plushie\\/a",
          "prices": [
            {
              "currency": {
                "gamelink": "\\aITEM -364189726 2052492544 0 0 0:Beer Token\\/a",
                "amount": 4
              }
            }
          ]
        },
        {
          "gamelink": "\\aITEM 1285946621 1841260258 0 0 0:Golden Warboar\\/a",
          "prices": [
            {
              "currency": {
                "gamelink": "\\aITEM -364189726 2052492544 0 0 0:Beer Token\\/a",
                "amount": 100
              }
            }
          ]
        },
        {
          "gamelink": "\\aITEM -1326810330 748253807 0 0 0:Green Field Square\\/a",
          "prices": [
            {
              "coin": 10000
            }
          ]
        },
        {
          "gamelink": "\\aITEM -566548644 -39459557 0 0 0:Green Stained Glass Square\\/a",
          "prices": [
            {
              "coin": 10000
            }
          ]
        },
        {
          "gamelink": "\\aITEM 558195329 2110243299 0 0 0:Grikbar Hero\\/a",
          "prices": [
            {
              "currency": {
                "gamelink": "\\aITEM -364189726 2052492544 0 0 0:Beer Token\\/a",
                "amount": 5
              }
            }
          ]
        },
        {
          "gamelink": "\\aITEM 1824926659 -240130662 0 0 0:Grikbar Shaman's Provisions\\/a",
          "prices": [
            {
              "currency": {
                "gamelink": "\\aITEM -364189726 2052492544 0 0 0:Beer Token\\/a",
                "amount": 2
              }
            }
          ]
        },
        {
          "gamelink": "\\aITEM -1718466519 -1274094874 0 0 0:Grobb Stone Bar\\/a",
          "prices": [
            {
              "currency": {
                "gamelink": "\\aITEM -364189726 2052492544 0 0 0:Beer Token\\/a",
                "amount": 5
              }
            }
          ]
        },
        {
          "gamelink": "\\aITEM -1484410073 1422515881 0 0 0:Hammerstein Replica\\/a",
          "prices": [
            {
              "currency": {
                "gamelink": "\\aITEM -364189726 2052492544 0 0 0:Beer Token\\/a",
                "amount": 5
              }
            }
          ]
        },
        {
          "gamelink": "\\aITEM -1396039501 -1362462829 0 0 0:Healthy Hops Vine\\/a",
          "prices": [
            {
              "currency": {
                "gamelink": "\\aITEM -364189726 2052492544 0 0 0:Beer Token\\/a",
                "amount": 4
              }
            }
          ]
        },
        {
          "gamelink": "\\aITEM 776381094 -1631018916 0 0 0:Hewn Stone Bridge\\/a",
          "prices": [
            {
              "currency": {
                "gamelink": "\\aITEM -364189726 2052492544 0 0 0:Beer Token\\/a",
                "amount": 30
              }
            }
          ]
        },
        {
          "gamelink": "\\aITEM -904274788 -1198863734 0 0 0:Hinged Ancient Kaladim Hatch\\/a",
          "prices": [
            {
              "currency": {
                "gamelink": "\\aITEM -364189726 2052492544 0 0 0:Beer Token\\/a",
                "amount": 15
              }
            }
          ]
        },
        {
          "gamelink": "\\aITEM -1026914244 500423811 0 0 0:Hinged Blackburrow Rocking Barrel\\/a",
          "prices": [
            {
              "currency": {
                "gamelink": "\\aITEM -364189726 2052492544 0 0 0:Beer Token\\/a",
                "amount": 15
              }
            }
          ]
        },
        {
          "gamelink": "\\aITEM -2079929191 1984267198 0 0 0:Hinged Wine Rack\\/a",
          "prices": [
            {
              "currency": {
                "gamelink": "\\aITEM -364189726 2052492544 0 0 0:Beer Token\\/a",
                "amount": 15
              }
            }
          ]
        },
        {
          "gamelink": "\\aITEM -191758120 -1365826586 0 0 0:Inebriated Brewday Celebrator – Seated Lad\\/a",
          "prices": [
            {
              "currency": {
                "gamelink": "\\aITEM -364189726 2052492544 0 0 0:Beer Token\\/a",
                "amount": 8
              }
            }
          ]
        },
        {
          "gamelink": "\\aITEM -1591410306 1612585462 0 0 0:Inebriated Brewday Celebrator – Seated Lady\\/a",
          "prices": [
            {
              "currency": {
                "gamelink": "\\aITEM -364189726 2052492544 0 0 0:Beer Token\\/a",
                "amount": 8
              }
            }
          ]
        },
        {
          "gamelink": "\\aITEM -1613335224 1428529048 0 0 0:Kaladim Brewing Tanks\\/a",
          "prices": [
            {
              "currency": {
                "gamelink": "\\aITEM -364189726 2052492544 0 0 0:Beer Token\\/a",
                "amount": 15
              }
            }
          ]
        },
        {
          "gamelink": "\\aITEM -113850075 1530928969 0 0 0:Kaladim Stone Stout\\/a",
          "prices": [
            {
              "currency": {
                "gamelink": "\\aITEM -364189726 2052492544 0 0 0:Beer Token\\/a",
                "amount": 2
              }
            }
          ]
        },
        {
          "gamelink": "\\aITEM -1787422907 -2076676866 0 0 0:Kobold Bed\\/a",
          "prices": [
            {
              "currency": {
                "gamelink": "\\aITEM -364189726 2052492544 0 0 0:Beer Token\\/a",
                "amount": 5
              }
            }
          ]
        },
        {
          "gamelink": "\\aITEM -1234147768 1397764044 0 0 0:Living Rootball\\/a",
          "prices": [
            {
              "currency": {
                "gamelink": "\\aITEM -364189726 2052492544 0 0 0:Beer Token\\/a",
                "amount": 10
              }
            }
          ]
        },
        {
          "gamelink": "\\aITEM -458473209 -855630561 0 0 0:Locked Barrel Room\\/a",
          "prices": [
            {
              "currency": {
                "gamelink": "\\aITEM -364189726 2052492544 0 0 0:Beer Token\\/a",
                "amount": 80
              }
            }
          ]
        },
        {
          "gamelink": "\\aITEM 90889326 1476606780 0 0 0:Malduran Warboar\\/a",
          "prices": [
            {
              "currency": {
                "gamelink": "\\aITEM -364189726 2052492544 0 0 0:Beer Token\\/a",
                "amount": 100
              }
            }
          ]
        },
        {
          "gamelink": "\\aITEM -1994412477 -496862755 0 0 0:Miner's Illuminating Gem\\/a",
          "prices": [
            {
              "currency": {
                "gamelink": "\\aITEM -364189726 2052492544 0 0 0:Beer Token\\/a",
                "amount": 5
              }
            }
          ]
        },
        {
          "gamelink": "\\aITEM 1089875528 1598903437 0 0 0:Mineral Warrior Plushie\\/a",
          "prices": [
            {
              "currency": {
                "gamelink": "\\aITEM -364189726 2052492544 0 0 0:Beer Token\\/a",
                "amount": 4
              }
            }
          ]
        },
        {
          "gamelink": "\\aITEM 766411994 -1689124934 0 0 0:Mossy Stalagmaw\\/a",
          "prices": [
            {
              "currency": {
                "gamelink": "\\aITEM -364189726 2052492544 0 0 0:Beer Token\\/a",
                "amount": 10
              }
            }
          ]
        },
        {
          "gamelink": "\\aITEM -2075845356 -769074860 0 0 0:Nightfury Griffin\\/a",
          "prices": [
            {
              "currency": {
                "gamelink": "\\aITEM -364189726 2052492544 0 0 0:Beer Token\\/a",
                "amount": 200
              }
            }
          ]
        },
        {
          "gamelink": "\\aITEM -887175818 -743528585 0 0 0:Petamorph Wand: Animated Hops\\/a",
          "prices": [
            {
              "currency": {
                "gamelink": "\\aITEM -364189726 2052492544 0 0 0:Beer Token\\/a",
                "amount": 15
              }
            }
          ]
        },
        {
          "gamelink": "\\aITEM 1204606681 -1241132371 0 0 0:Petamorph Wand: Coastal Basilisk\\/a",
          "prices": [
            {
              "currency": {
                "gamelink": "\\aITEM -364189726 2052492544 0 0 0:Beer Token\\/a",
                "amount": 15
              }
            }
          ]
        },
        {
          "gamelink": "\\aITEM -271394157 -2070039736 0 0 0:Petamorph Wand: Cursed Dhalgar Skeleton\\/a",
          "prices": [
            {
              "currency": {
                "gamelink": "\\aITEM -364189726 2052492544 0 0 0:Beer Token\\/a",
                "amount": 15
              }
            }
          ]
        },
        {
          "gamelink": "\\aITEM -2073236892 1343781891 0 0 0:Petamorph Wand: Fossilfang Rumbler\\/a",
          "prices": [
            {
              "currency": {
                "gamelink": "\\aITEM -364189726 2052492544 0 0 0:Beer Token\\/a",
                "amount": 15
              }
            }
          ]
        },
        {
          "gamelink": "\\aITEM 773207812 916870405 0 0 0:Petamorph Wand: Malduran Slug\\/a",
          "prices": [
            {
              "currency": {
                "gamelink": "\\aITEM -364189726 2052492544 0 0 0:Beer Token\\/a",
                "amount": 15
              }
            }
          ]
        },
        {
          "gamelink": "\\aITEM 798187667 -1292128235 0 0 0:Petamorph Wand: Malduran Warboar\\/a",
          "prices": [
            {
              "currency": {
                "gamelink": "\\aITEM -364189726 2052492544 0 0 0:Beer Token\\/a",
                "amount": 15
              }
            }
          ]
        },
        {
          "gamelink": "\\aITEM -1811595271 -1231163586 0 0 0:Petamorph Wand: Mossy Stalagmaw\\/a",
          "prices": [
            {
              "currency": {
                "gamelink": "\\aITEM -364189726 2052492544 0 0 0:Beer Token\\/a",
                "amount": 15
              }
            }
          ]
        },
        {
          "gamelink": "\\aITEM -2032038418 1440943491 0 0 0:Petamorph Wand: Stonescale Basilisk\\/a",
          "prices": [
            {
              "currency": {
                "gamelink": "\\aITEM -364189726 2052492544 0 0 0:Beer Token\\/a",
                "amount": 15
              }
            }
          ]
        },
        {
          "gamelink": "\\aITEM 861761342 -1451043931 0 0 0:Petamorph Wand: Underdepths Stalagmaw\\/a",
          "prices": [
            {
              "currency": {
                "gamelink": "\\aITEM -364189726 2052492544 0 0 0:Beer Token\\/a",
                "amount": 15
              }
            }
          ]
        },
        {
          "gamelink": "\\aITEM 1430785628 98588878 0 0 0:Pickclaw Goblin Plushie\\/a",
          "prices": [
            {
              "currency": {
                "gamelink": "\\aITEM -364189726 2052492544 0 0 0:Beer Token\\/a",
                "amount": 4
              }
            }
          ]
        },
        {
          "gamelink": "\\aITEM -679170709 2117909554 0 0 0:Pot of Wake-up Juice\\/a",
          "prices": [
            {
              "currency": {
                "gamelink": "\\aITEM -364189726 2052492544 0 0 0:Beer Token\\/a",
                "amount": 5
              }
            }
          ]
        },
        {
          "gamelink": "\\aITEM -1155455567 672121904 0 0 0:Rug of Pour Choices\\/a",
          "prices": [
            {
              "currency": {
                "gamelink": "\\aITEM -364189726 2052492544 0 0 0:Beer Token\\/a",
                "amount": 20
              }
            }
          ]
        },
        {
          "gamelink": "\\aITEM -759323274 -760632131 0 0 0:Runnyeye Shinykeeper Plushie\\/a",
          "prices": [
            {
              "currency": {
                "gamelink": "\\aITEM -364189726 2052492544 0 0 0:Beer Token\\/a",
                "amount": 4
              }
            }
          ]
        },
        {
          "gamelink": "\\aITEM -1490553053 1249913160 0 0 0:Seal of Maldura\\/a",
          "prices": [
            {
              "currency": {
                "gamelink": "\\aITEM -364189726 2052492544 0 0 0:Beer Token\\/a",
                "amount": 10
              }
            }
          ]
        },
        {
          "gamelink": "\\aITEM -1485841783 1990028750 0 0 0:Slobberjaw Hero\\/a",
          "prices": [
            {
              "currency": {
                "gamelink": "\\aITEM -364189726 2052492544 0 0 0:Beer Token\\/a",
                "amount": 5
              }
            }
          ]
        },
        {
          "gamelink": "\\aITEM 1591101885 985384590 0 0 0:Snowfang Thief Plushie\\/a",
          "prices": [
            {
              "currency": {
                "gamelink": "\\aITEM -364189726 2052492544 0 0 0:Beer Token\\/a",
                "amount": 4
              }
            }
          ]
        },
        {
          "gamelink": "\\aITEM 790937478 1940266212 0 0 0:Spilled Beer\\/a",
          "prices": [
            {
              "currency": {
                "gamelink": "\\aITEM -364189726 2052492544 0 0 0:Beer Token\\/a",
                "amount": 10
              }
            }
          ]
        },
        {
          "gamelink": "\\aITEM 1816924528 -1034444090 0 0 0:Underfoot Debris\\/a",
          "prices": [
            {
              "currency": {
                "gamelink": "\\aITEM -364189726 2052492544 0 0 0:Beer Token\\/a",
                "amount": 10
              }
            }
          ]
        },
        {
          "gamelink": "\\aITEM 1146262481 1977095228 0 0 0:Wake-up Juice\\/a",
          "prices": [
            {
              "currency": {
                "gamelink": "\\aITEM -364189726 2052492544 0 0 0:Beer Token\\/a",
                "amount": 1
              }
            }
          ]
        },
        {
          "gamelink": "\\aITEM -1631482788 -666427010 0 0 0:Wild Boar\\/a",
          "prices": [
            {
              "currency": {
                "gamelink": "\\aITEM -364189726 2052492544 0 0 0:Beer Token\\/a",
                "amount": 30
              }
            }
          ]
        },
        {
          "gamelink": "\\aITEM -1343816738 -691629685 0 0 0:Woven Circular Rug of Inebriation\\/a",
          "prices": [
            {
              "currency": {
                "gamelink": "\\aITEM -364189726 2052492544 0 0 0:Beer Token\\/a",
                "amount": 20
              }
            }
          ]
        }
      ]
    },
    {
      "name": "Dustaine",
      "name_sortable": "dustaine",
      "purpose": "The Burglars",
      "locations": [
        "360.93,-21.0,139.4"
      ]
    },
    {
      "name": "Edvan",
      "name_sortable": "edvan",
      "purpose": "The Burglars",
      "locations": [
        "357.6,-21.0,137.03"
      ]
    },
    {
      "name": "Gergy Gigglegibber",
      "name_sortable": "gergygigglegibber",
      "locations": [
        "357.43,-20.99,146.39"
      ],
      "utterances": [
        "Happy, happy Brelly Day!"
      ]
    },
    {
      "name": "Gilin Rockbreath",
      "name_sortable": "gilinrockbreath",
      "locations": [
        "356.38,-21.0,142.01"
      ],
      "utterances": [
        "Grab yerself a pint and enjoy the day, <player name>!  Who knows ye just might find a pretty young thing to grapple with by the end of it.",
        "You bet it... Whoa!  Speak of the demon.  She is a looker!  Be still me hammerin' heart!  What mines has she been hidin' in all me life?!",
        "That vision of perfection, over yonder.  The amber haired beauty, that's who!",
        "What?!  Me eyes are keen, and I ain't drunk enough to see what ain't there.  Wait one gods forsaken moment!",
        "Do you see anyone over yonder, standing in the corner?",
        "Don't ya talk about me love like that!",
        "Aaagh!  Damned gnome gadgetry!  Ye can never trust ‘em!  I should just be thankful that them goggles didn't simply blow up in me face, especially while I was enjoying those gorgeous ladies abroad.",
        "Oh, blessed Brell!  What if those ladies weren't as lovely as I thought?  But I can't show me face around them again if'n they be hideous.  You can do it for me!",
        "Go back and find each lass and let me know if'n they be hot or not.  Take the goggles and be sure you find the exact filly I saw.  Tell them whatever ya will, but don't ya dare say that yer checkin' them out for me!",
        "I'll be eternally grateful to you for findin' out if those lasses be sweet on me eyes or not.",
        "Am I glad to see you, <player name>!  Tell me, were any of those lasses as gorgeous as I thought they were.",
        "The Dwarf lass with the crimson mane?",
        "Ye've made my heart sing once more, <player name>!  And I'll steer clear of them other fillies from this day forward.  Thank you, and take this as a token of me appreciations."
      ]
    },
    {
      "name": "Goober",
      "name_sortable": "goober",
      "utterances": [
        "Still working!  Need more patiences from you."
      ]
    },
    {
      "name": "Groden",
      "name_sortable": "groden",
      "purpose": "The Burglars",
      "locations": [
        "357.81,-21.0,139.5"
      ]
    },
    {
      "name": "Mraugl Stonecrusher",
      "name_sortable": "mrauglstonecrusher",
      "purpose": "Bartender",
      "locations": [
        "351.0,-20.99,151.23"
      ],
      "utterances": [
        "Oi there! You hear that racket?"
      ],
      "store": [
        {
          "gamelink": "\\aITEM -376704030 -1941389211 0 0 0:Ale\\/a",
          "prices": [
            {
              "coin": 120
            }
          ]
        },
        {
          "gamelink": "\\aITEM 1618656513 -631993083 0 0 0:Antonia Ale (Alcoholic)\\/a",
          "prices": [
            {
              "coin": 120
            }
          ]
        },
        {
          "gamelink": "\\aITEM -1934096785 -287274111 0 0 0:Brell's Own Brew (Alcoholic)\\/a",
          "prices": [
            {
              "coin": 16800
            }
          ]
        },
        {
          "gamelink": "\\aITEM 1281187795 -495418410 0 0 0:Dwarven Ale (Alcoholic)\\/a",
          "prices": [
            {
              "coin": 600
            }
          ]
        },
        {
          "gamelink": "\\aITEM 1645837523 -1882614395 0 0 0:Dwarven Language Primer\\/a",
          "prices": [
            {
              "coin": 1200
            }
          ]
        },
        {
          "gamelink": "\\aITEM -692542167 450719094 0 0 0:Elven Wine (Alcoholic)\\/a",
          "prices": [
            {
              "coin": 720
            }
          ]
        },
        {
          "gamelink": "\\aITEM 1608751314 -1346962995 0 0 0:Gnomish Spirits (Alcoholic)\\/a",
          "prices": [
            {
              "coin": 840
            }
          ]
        },
        {
          "gamelink": "\\aITEM -1424677497 801220853 0 0 0:Lucan's Lager (Alcoholic)\\/a",
          "prices": [
            {
              "coin": 120
            }
          ]
        },
        {
          "gamelink": "\\aITEM 1199073772 520539661 0 0 0:Oggok Swill (Alcoholic)\\/a",
          "prices": [
            {
              "coin": 1200
            }
          ]
        },
        {
          "gamelink": "\\aITEM 1383852152 -1014417461 0 0 0:Teir'dal Blood Wine (Alcoholic)\\/a",
          "prices": [
            {
              "coin": 1080
            }
          ]
        }
      ]
    },
    {
      "name": "Oldar Foambeard",
      "name_sortable": "oldarfoambeard",
      "locations": [
        "330.95,-20.99,143.49"
      ],
      "utterances": [
        "Well met!  What brings ya to this mystical watering hole?",
        "Ya'd win that wager, fer certain.  Though yer gonna be disappointed if'n ya like anything stronger than fermented river water.",
        "The amount of swill that's passed me lips over me many years is great, and what they've got here ranks amongst the better, I must admit.  But Thurgadin Ice Brew is still the best there be!  Punch ya in the gut and leave ya head in tomorrow, it will!",
        "Good thinking!  I like the way your mind works, <player name>.  Get us some Dwarven Ale from the bartender."
      ]
    },
    {
      "name": "a patron",
      "name_sortable": "patron",
      "locations": [
        "345.94,-20.51,142.86",
        "351.99,-20.99,135.05",
        "358.77,-21.0,142.23",
        "336.82,-20.58,152.15"
      ],
      "utterances": [
        "Good day to you!"
      ]
    },
    {
      "name": "Rasel Alechaser",
      "name_sortable": "raselalechaser",
      "purpose": "Brewer",
      "locations": [
        "353.05,-20.99,148.01"
      ],
      "utterances": [
        "Another ale!",
        "Hey you! Ye look like ya know a good drink... Ye should help me out with somethin'.",
        "Yer a funny one... It's Brewday, ye should be a bit more respectaful to your elders. Now if you're done flapping your gums, I'll present my offer to ya.",
        "I'm the most respectaficated brewer since me great, great, great grandfather's uncle's nephew, Barnaby Beerswiller. Me old ancestor Barnaby is most famous for brewing Brell's Everlasting Brew. No one 'ere believes the brew exists, but I know it does!",
        "Barnaby passed on the recipe from Brell's hands down to our family. I have it, but finding the ingredients is just a little beyond me at the moment. If ye agree to help me, I'll give ye a keg of the brew. What do ya say?"
      ]
    },
    {
      "name": "a rowdy patron",
      "name_sortable": "rowdypatron",
      "locations": [
        "336.23,-26.99,149.39",
        "343.42,-26.99,149.9"
      ]
    },
    {
      "name": "Snoogle Blitzed",
      "name_sortable": "snoogleblitzed",
      "purpose": "Inventor",
      "locations": [
        "336.91,-20.99,137.39"
      ],
      "utterances": [
        "The only thing more fun than being in Brell's Bar is having you with me, Buzzed.",
        "I wonder why they won't let us down stairs?",
        "Give me another one Buzz, or I'll take your bolts out.",
        "We have such a good time together.",
        "Once again, you follow me here. Some day I will leave you alone.",
        "Well, hello there!",
        "Oh, I did. Well then, you must need a drink.",
        "Hey Buzzer, pour this one some of your special stuff.",
        "Sure you do! It is a most wonderful clockwork concoction.",
        "Oh, I am sorry we must have already met. See I am just so lost in thought.",
        "Well, yes I am that too. I must remember where I left them and what I did, and I was on my way to Brell's bar when I think I left them.",
        "I have, over the years of INTENSELY studying Brewday, come up with four objects that hold great power during the Brewday festival.",
        "Oh no, I could be, but I have a huge presentation tomorrow about the very subject, and if I drink the Gnomish Spirits required to be in the state where the powers show themselves, I will never make the presentation.",
        "Yes, yes. And if you drink from it, you will be able to see the objects of great power.",
        "I am not sure I can trust you with it. If you knew, you could give the presentation to the council. And then where would I be?",
        "Oh, you're a tricky one you are.",
        "Well, hello there.",
        "Help with what?",
        "I did? Well, you will need this then. It's my flask. If you lose it I will be very angry. But let me tell you a secret. These things you are after, you can only see them once you've taken a sip from my flask!",
        "The first object of power lies in the savanna, but it can only be seen under the right circumstances. It follows its own kind, although much smaller in size.",
        "The next flies in the sky above its home. It seems silly to its siblings and to the ones it knows. Even the dead around cannot help but laugh when it oinks.",
        "Hello, did you bring that for me?",
        "Oh, silly that. It's small and fast and has a tail, but when you catch it you will know its power. I last saw it on a beach coloring its scales. But it ran away too fast for me to gather.",
        "It talks to you and yet it should not. It goes great with corned beef and a brew. But when it talks to you... ewww...",
        "Oh yeah, it grows in a very enchanted place, and the one with the tail lives on the outskirts of the jungle. The flying one lives above a small village in the hills, and I think I told you where to find the first one.",
        "Well, hello there! Take my flask, I think I forgot to give it to you earlier. You remember how to use it don't you? It's so wonderful.",
        "How many more pints do you have Buzzed? .... Really? Well I should get to drinking then.",
        "I love you my best mechanical buddy, Buzzed!",
        "Who are you again?",
        "Well, hello there! Enjoying my Flying Kegerator, are you?",
        "Out already!? I was working on a new ale porter. It must have been a very popular clockwork concoction if Buzzed is empty already!",
        "I've got everything needed to brew some more, except Seamist malt and Haoaera pepper.",
        "Oh my, yes! But don't you worry, I'll get Buzzed filled with the other components. We're just counting on you!",
        "Once you get the malt and pepper just add 'em to Buzzed and my Flying Kegerator will do the rest!"
      ]
    },
    {
      "name": "Steinmaster Borric",
      "name_sortable": "steinmasterborric",
      "purpose": "a cleric of Serillis",
      "locations": [
        "339.9,-20.99,140.27"
      ],
      "utterances": [
        "You'll wanna' grab another ale. The Duke of Below's altar I'm assemblin' ain't quite ready for yer prayers, just yet.",
        "I'm lookin' to incorporate different items from a slew of Brell's creations. Whether we wanna' admit it or not, he's had his hand in sculptin' a great many of us into being.",
        "You and your Agents wanna' help me gather up the items? I'll light a candle for ya, when it's done.",
        "I trust you and your capable Agents will help obtain the different items I seek for the altar."
      ]
    },
    {
      "name": "Tellar Blackswell",
      "name_sortable": "tellarblackswell",
      "locations": [
        "332.54,-20.99,147.36"
      ],
      "utterances": [
        "Well met!  Oh, wow.  Is the room spinning for you too?",
        "You're right about that!  Ha ha ha!  I was on my way somewhere... when the sound of intoxicated dwarven mirth called me to the Bar of Brell.  Where was I going?",
        "I'm in no shape to leave now, that's for sure!  But maybe if I was sober I would remember where I was going and what I was doing.",
        "There's a wondrous tonic sold by Eurkon Al'ouz, a sarnak in Gorowyn.  I tell you, his Gorowyn Pepper Swill always sobers me right up!"
      ]
    },
    {
      "name": "Toast",
      "name_sortable": "toast",
      "utterances": [
        "*neigh*"
      ]
    },
    {
      "name": "Valla Brewhammer",
      "name_sortable": "vallabrewhammer",
      "locations": [
        "339.15,-20.99,151.19"
      ],
      "utterances": [
        "Ya'd never believe what I can brew!",
        "Ya definitely get carried away with what I can brew.",
        "Oh, ya think I'll spill me secrets as simple as that, eh?  I know how to hold me drink and me secrets!",
        "HA!  Ya got a good wit about ya, I'll give ya that, <player name>!",
        "I'll tell ya what, bring me the right items and I'll brew ya up a nice reward.  That'll answer yur question, for sure!",
        "I'll tell ya in riddle.  Ya gotta figure it out and get me the items."
      ]
    }
  ],
  "shinies": [
    {
      "gamelink": "\\aITEM -1156858540 -845604802:Bog Water Brew\\/a",
      "locations": [
        "328.57,-20.07,143.21",
        "342.54,-14.49,151.00",
        "333.85,-20.99,145.61",
        "335.47,-26.99,147.50",
        "339.41,-20.99,142.82"
      ]
    },
    {
      "gamelink": "\\aITEM -1930407733 1874842855:Miner's Milk\\/a",
      "locations": [
        "339.41,-20.99,142.82",
        "341.76,-20.99,153.38",
        "334.03,-26.99,157.90"
      ]
    },
    {
      "gamelink": "\\aITEM -1880231903 -448458293:Somborn Sanguine Ale\\/a",
      "locations": [
        "333.85,-20.99,145.61",
        "339.41,-20.99,142.82",
        "328.57,-20.07,143.21",
        "345.92,-26.99,151.12",
        "340.63,-26.99,148.84"
      ]
    }
  ]
}