[
	{
		"id": 1920961799,
		"name": "Far Seas Direct Requisition #FRN0378",
		"giver_item": {
			"id": 2541639473,
			"name": "Far Seas Trading Requisition FRN0378"
		}
	},
	{
		"id": 3950435517,
		"name": "Far Seas Direct Requisition #FRN0931",
		"giver_item": {
			"id": 2270801735,
			"name": "Far Seas Trading Requisition FRN0931"
		}
	},
	{
		"id": 137609204,
		"name": "News for Germain",
		"next_quest": {
			"id": 2436558414,
			"name": "Favors"
		}
	},
	{
		"name": "Restocking Bog Faeire Wings",
		"category": "Nettleville Hovel"
	},
	{
		"name": "Toxic Glands for Erollisi's Bane",
		"category": "Nettleville Hovel"
	},
	{
		"name": "Refill the Oakmyst Spider Silk Jars",
		"category": "Nettleville Hovel"
	},
	{
		"name": "Vida Needs a New Broom",
		"category": "Nettleville Hovel"
	},
	{
		"name": "Anti-venom Components for Brendan",
		"category": "North Qeynos"
	},
	{
		"name": "Qeynosian Civil Service",
		"category": "North Qeynos"
	},
	{
		"name": "Gnoll Extermination",
		"category": "North Qeynos"
	},
	{
		"id": 4133302910,
		"category": "Commonlands",
		"name": "The Chamber of Suffering",
		"level": 18,
		"shareable": false,
		"removed": true,
		"starter_text": "I found a rust covered key in the Commonlands.",
		"completion_text": "I used the key to open the mausoleum in the Commonlands.",
		"stages": [
			{
				"starter_text": "I need to find the mausoleum that this key unlocks.",
				"completion_text": "I found the mausoleum related to the key."
			},
			{
				"starter_text": "I need to enter the Chamber of Suffering.",
				"completion_text": "I have entered the Chamber of Suffering."
			}
		]
	},
	{
		"id": 2535915598,
		"name": "Blessings of Growth: Commonlands",
		"removed": true
	},
	{
		"id": 319882287,
		"name": "The Bloodthirsty Coin",
		"removed": true
	},
	{
		"id": 2143836112,
		"name": "The Bloody Fist Wrap",
		"removed": true
	},
	{
		"id": 2760250377,
		"name": "The Chamber of Suffering",
		"removed": true
	},
	{
		"id": 1251708323,
		"name": "Front Yard Cleanup",
		"removed": true
	},
	{
		"id": 2721716912,
		"name": "Guard N'Garen's Unrest with Safiya",
		"removed": true
	},
	{
		"id": 1751115295,
		"name": "Steelbone Family Scroll",
		"removed": true
	},
	{
		"id": 993217290,
		"name": "Saving Safiya",
		"removed": true
	},
	{
		"id": 1795075380,
		"name": "Fish meat...?",
		"removed": true
	},
	{
		"id": 2852570471,
		"name": "Recycled Wood",
		"removed": true
	},
	{
		"id": 746284539,
		"name": "Perfection in a Pot",
		"removed": true
	},
	{
		"id": 2596868760,
		"name": "You Can't Beat Me If You Can't Find Me",
		"removed": true
	},
	{
		"id": 1657134264,
		"name": ":jq_pt_title",
		"removed": true
	},
	{
		"id": 634539204,
		"name": ":jq_title",
		"removed": true
	},
	{
		"id": 2092381222,
		"name": "nwalling test",
		"removed": true
	},
	{
		"id": 3266521554,
		"name": "Test",
		"removed": true
	},
	{
		"id": 3163629401,
		"name": "test harvest quest",
		"removed": true
	},
	{
		"id": 689303480,
		"name": "Test Max Currency",
		"removed": true
	},
	{
		"id": 473115660,
		"name": "Test Max Currency",
		"removed": true
	},
	{
		"id": 1056332529,
		"name": "kill rat",
		"removed": true
	},
	{
		"id": 1114801625,
		"name": "Test TCI Hide",
		"removed": true
	},
	{
		"id": 1919766803,
		"name": "Test",
		"removed": true
	},
	{
		"id": 3191697966,
		"name": "Fail Timer - Remove with Popup",
		"removed": true
	},
	{
		"id": 162622876,
		"name": "Effect - Betrayal Curse",
		"removed": true
	},
	{
		"id": 3414519646,
		"name": "Fail Timer - Default Previous Stage",
		"removed": true
	},
	{
		"name": "[NO NAME]",
		"removed": true
	}
]
